music_scraper
