Metadata-Version: 1.0
Name: music-scraper
Version: 1.1.0
Summary: Gets Songs from the web and allows users to download the same
Home-page: https://github.com/srivatsan-ramesh/Music-Scraper
Author: srivatsan-ramesh
Author-email: sriramesh4@gmail.com
License: MIT
Platform: UNKNOWN
